{
  "name": "Subtly Skilled",
  "type": "feature",
  "img": "icons/creatures/magical/humanoid-silhouette-dashing-blue.webp",
  "effects": [],
  "flags": {},
  "system": {
    "ac": {
      "baseFormula": "",
      "formula": "",
      "maxDex": 0,
      "minStr": 0,
      "mode": 2,
      "requiresNoShield": false,
      "requiresUnarmored": false
    },
    "actions": {},
    "description": "<p>A nightstalker’s true strength isn’t brute force—you are an infiltrator, deceiver, a voice in the right ear or a knife to the right neck, and you turn your physical and mental discipline into the subtlest of manipulations and subterfuge.&nbsp;</p><p>You may add your martial arts die as a bonus to Acrobatics, Culture, Deception, Engineering, Intimidation, Investigation, Sleight of Hand, Stealth, Perception, Performance, and Persuasion checks.&nbsp;&nbsp;&nbsp;</p>",
    "favorite": false,
    "secretDescription": "",
    "source": "adventurersGuide",
    "uses": {
      "value": null,
      "max": "",
      "per": null,
      "recharge": {
        "formula": "1d6",
        "threshold": 6
      }
    },
    "schema": {
      "version": null,
      "lastMigration": null
    },
    "concentration": false,
    "featureType": "feat",
    "grants": {},
    "prerequisite": "Nightstalker feat",
    "requiresBloodied": false,
    "schemaVersion": {
      "version": 0.013,
      "lastMigration": {
        "version": {
          "schema": 0.011,
          "foundry": "11.315",
          "system": "0.16.49"
        }
      }
    }
  },
  "folder": null,
  "_id": "1vnsypg3bcs1itkh"
}
