{
	"folder": null,
	"name": "Escape Beam",
	"type": "feature",
	"img": "icons/magic/control/silhouette-grow-shrink-blue.webp",
	"system": {
		"ac": {
			"baseFormula": "",
			"formula": "",
			"grantsDisadvantage": false,
			"maxDex": 0,
			"minStr": 0,
			"mode": 2,
			"requiresNoShield": false,
			"requiresUnarmored": false
		},
		"actions": {
			"ZbV5p5L0M6quECMf": {
				"name": "Escape Beam",
				"consumers": {
					"ZO1h2QNlU48R5h87": {
						"type": "itemUses",
						"default": true,
						"quantity": 1,
						"label": ""
					}
				},
				"activation": {
					"type": "action",
					"cost": 1,
					"reactionTrigger": ""
				},
				"target": {
					"type": "creature",
					"quantity": 5,
					"scaling": {}
				},
				"id": "",
				"default": false,
				"description": "",
				"descriptionOutputs": [
					"item",
					"action"
				],
				"img": "",
				"duration": {
					"unit": "",
					"value": 0
				},
				"effects": [],
				"prompts": {},
				"ranges": {},
				"rolls": {},
				"uses": {
					"value": 0,
					"max": "",
					"per": "",
					"recharge": {
						"formula": "",
						"threshold": 0
					}
				}
			}
		},
		"description": "<p>Once between long rests, as an action you can teleport yourself back to the deck of a spaceship you have crewed in the last 48 hours.&nbsp;You can bring up to 5 willing creatures within reach.&nbsp;The destination spaceship must be in the same star system as you.</p>",
		"favorite": false,
		"secretDescription": "",
		"source": "voidrunnersCodex",
		"uses": {
			"value": 1,
			"max": "1",
			"per": "longRest",
			"recharge": {
				"formula": "",
				"threshold": 0
			}
		},
		"concentration": false,
		"featureType": "knack",
		"grants": {},
		"prerequisite": "11th level",
		"requiresBloodied": false,
		"class": "",
		"classes": "scientist",
		"migrationData": {
			"version": 0.019,
			"lastMigration": {
				"system": null,
				"foundry": null,
				"schema": null
			},
			"type": ""
		}
	},
	"effects": [],
	"flags": {},
	"_stats": {
		"coreVersion": "12.331",
		"systemId": "a5e",
		"systemVersion": "0.19.32",
		"createdTime": 1733520377223,
		"modifiedTime": 1733668633403,
		"lastModifiedBy": "Glw114cHAVexdKTu"
	},
	"_id": "6bWAWQs036trZ9EK"
}