{
	"folder": null,
	"name": "Orbital Artillery",
	"type": "feature",
	"img": "icons/magic/holy/projectiles-blades-salvo-yellow.webp",
	"system": {
		"ac": {
			"baseFormula": "",
			"formula": "",
			"grantsDisadvantage": false,
			"maxDex": 0,
			"minStr": 0,
			"mode": 2,
			"requiresNoShield": false,
			"requiresUnarmored": false
		},
		"actions": {
			"nWihZlJBjVf03eWa": {
				"name": "Orbital Artillery",
				"activation": {
					"type": "action",
					"cost": 1,
					"reactionTrigger": ""
				},
				"consumers": {
					"Mgt4q86MOKFUeBH2": {
						"type": "itemUses",
						"default": true,
						"quantity": 1,
						"label": ""
					}
				},
				"rolls": {
					"17kkdItyw4Vr0iYX": {
						"type": "damage",
						"default": true,
						"formula": "6d6",
						"damageType": "fire",
						"label": "",
						"canCrit": false,
						"scaling": {
							"mode": null,
							"step": 2,
							"formula": "4"
						},
						"critBonus": ""
					},
					"SWxbT5yK3TBYiiIW": {
						"type": "damage",
						"default": true,
						"formula": "6d6",
						"damageType": "bludgeoning",
						"label": "",
						"canCrit": false,
						"scaling": {
							"mode": null,
							"formula": "4",
							"step": 2
						},
						"critBonus": ""
					}
				},
				"prompts": {
					"H2b4iKRRaxNHKinO": {
						"type": "savingThrow",
						"default": true,
						"ability": "dex",
						"saveDC": {
							"type": "int",
							"bonus": ""
						},
						"onSave": "Half damage",
						"label": ""
					},
					"Hv6eTr5HvpybIhWw": {
						"type": "effect",
						"default": true,
						"effectId": "Hg6lAbfkiiFzme5k"
					}
				},
				"uses": {
					"value": 0,
					"max": "",
					"per": "",
					"recharge": {
						"formula": "1d6",
						"threshold": 6
					}
				},
				"descriptionOutputs": [
					"action",
					"item"
				],
				"duration": {
					"unit": "",
					"value": 1
				},
				"target": {
					"type": "",
					"quantity": 1,
					"scaling": {}
				},
				"area": {
					"shape": "circle",
					"quantity": 1,
					"placeTemplate": true,
					"radius": 10
				},
				"ranges": {
					"cvCz6nT5MvWuzNye": {
						"range": "long"
					}
				},
				"id": "nWihZlJBjVf03eWa",
				"default": true,
				"description": "",
				"img": "icons/magic/holy/projectiles-blades-salvo-yellow.webp",
				"effects": []
			},
			"VLlQGOrn1EcnPuSR": {
				"name": "Orbital Artillery (16th Level)",
				"activation": {
					"type": "action",
					"cost": 1,
					"reactionTrigger": ""
				},
				"consumers": {
					"Mgt4q86MOKFUeBH2": {
						"type": "itemUses",
						"default": true,
						"quantity": 1,
						"label": ""
					}
				},
				"rolls": {
					"17kkdItyw4Vr0iYX": {
						"type": "damage",
						"default": true,
						"formula": "10d6",
						"damageType": "fire",
						"label": "",
						"canCrit": false,
						"scaling": {
							"mode": null,
							"step": 2,
							"formula": "4"
						},
						"critBonus": ""
					},
					"SWxbT5yK3TBYiiIW": {
						"type": "damage",
						"default": true,
						"formula": "10d6",
						"damageType": "bludgeoning",
						"label": "",
						"canCrit": false,
						"scaling": {
							"mode": null,
							"formula": "4",
							"step": 2
						},
						"critBonus": ""
					}
				},
				"prompts": {
					"H2b4iKRRaxNHKinO": {
						"type": "savingThrow",
						"default": true,
						"ability": "dex",
						"saveDC": {
							"type": "int",
							"bonus": ""
						},
						"onSave": "Half damage",
						"label": ""
					},
					"Hv6eTr5HvpybIhWw": {
						"type": "effect",
						"default": true,
						"effectId": "Hg6lAbfkiiFzme5k"
					}
				},
				"uses": {
					"value": 0,
					"max": "",
					"per": "",
					"recharge": {
						"formula": "1d6",
						"threshold": 6
					}
				},
				"descriptionOutputs": [
					"action",
					"item"
				],
				"duration": {
					"unit": "",
					"value": 1
				},
				"target": {
					"type": "",
					"quantity": 1,
					"scaling": {}
				},
				"area": {
					"shape": "circle",
					"quantity": 1,
					"placeTemplate": true,
					"radius": 20
				},
				"ranges": {
					"cvCz6nT5MvWuzNye": {
						"range": "long"
					}
				},
				"id": "VLlQGOrn1EcnPuSR",
				"default": true,
				"description": "",
				"img": "icons/magic/holy/projectiles-blades-salvo-yellow.webp",
				"effects": []
			},
			"xxjhvNPObNZKYQyr": {
				"name": "Orbital Artillery (18th Level)",
				"activation": {
					"type": "action",
					"cost": 1,
					"reactionTrigger": ""
				},
				"consumers": {
					"Mgt4q86MOKFUeBH2": {
						"type": "itemUses",
						"default": true,
						"quantity": 1,
						"label": ""
					}
				},
				"rolls": {
					"17kkdItyw4Vr0iYX": {
						"type": "damage",
						"default": true,
						"formula": "14d6",
						"damageType": "fire",
						"label": "",
						"canCrit": false,
						"scaling": {
							"mode": null,
							"step": 2,
							"formula": "4"
						},
						"critBonus": ""
					},
					"SWxbT5yK3TBYiiIW": {
						"type": "damage",
						"default": true,
						"formula": "14d6",
						"damageType": "bludgeoning",
						"label": "",
						"canCrit": false,
						"scaling": {
							"mode": null,
							"formula": "4",
							"step": 2
						},
						"critBonus": ""
					}
				},
				"prompts": {
					"H2b4iKRRaxNHKinO": {
						"type": "savingThrow",
						"default": true,
						"ability": "dex",
						"saveDC": {
							"type": "int",
							"bonus": ""
						},
						"onSave": "Half damage",
						"label": ""
					},
					"Hv6eTr5HvpybIhWw": {
						"type": "effect",
						"default": true,
						"effectId": "Hg6lAbfkiiFzme5k"
					}
				},
				"uses": {
					"value": 0,
					"max": "",
					"per": "",
					"recharge": {
						"formula": "1d6",
						"threshold": 6
					}
				},
				"descriptionOutputs": [
					"action",
					"item"
				],
				"duration": {
					"unit": "",
					"value": 1
				},
				"target": {
					"type": "",
					"quantity": 1,
					"scaling": {}
				},
				"area": {
					"shape": "circle",
					"quantity": 1,
					"placeTemplate": true,
					"radius": 40
				},
				"ranges": {
					"cvCz6nT5MvWuzNye": {
						"range": 1,
						"unit": "miles"
					}
				},
				"id": "nWihZlJBjVf03eWa",
				"default": true,
				"description": "",
				"img": "icons/magic/holy/projectiles-blades-salvo-yellow.webp",
				"effects": []
			}
		},
		"description": "<p>You enjoy cover fire provided by an ally in orbit, such as a satellite station directing hijacked asteroids or a ship’s main gun. Your artillery has 4 shots, which recharge when you complete a long rest. As an action, you can launch up to all remaining shots, directing the target square for each within 120 feet.&nbsp;Each creature within 10 feet of a target square makes a Dexterity saving throw against your science save DC, taking 6d6 fire damage and 6d6 bludgeoning damage on a failed save, or half as much damage on a successful one. A creature in more than one area of effect is only affected by one impact.</p>\n<p>At 16th level, the damage improves to 10d6 fire and 10d6 bludgeoning. Each shot produces a 20-foot radius sphere.</p>\n<p>At 18th level, the damage improves to 14d6 fire and 14d6 bludgeoning. Each shot produces a 40-foot radius sphere and your range increases to 1 mile (or in space combat, within the same star system).</p>",
		"favorite": false,
		"secretDescription": "",
		"source": "voidrunnersCodex",
		"uses": {
			"value": 4,
			"max": "4",
			"per": "longRest",
			"recharge": {
				"formula": "",
				"threshold": 0
			}
		},
		"concentration": false,
		"featureType": "knack",
		"grants": {},
		"prerequisite": "14th level",
		"requiresBloodied": false,
		"class": "",
		"classes": "scientist",
		"migrationData": {
			"version": 0.019,
			"lastMigration": {
				"system": null,
				"foundry": null,
				"schema": null
			},
			"type": ""
		}
	},
	"effects": [],
	"flags": {},
	"_stats": {
		"coreVersion": "12.331",
		"systemId": "a5e",
		"systemVersion": "0.19.32",
		"createdTime": 1733520377355,
		"modifiedTime": 1734027981742,
		"lastModifiedBy": "Glw114cHAVexdKTu"
	},
	"_id": "Hhk71i0qmVs6LbN9"
}