{
	"name": "Outlander",
	"type": "background",
	"img": "icons/environment/wilderness/cave-entrance-rocky.webp",
	"system": {
		"description": "<p class=\"Indent1\"><strong>Ability Score Increases:</strong>&nbsp;+1 to Constitution and one other ability score.</p>\n<p class=\"Indent1\"><strong>Skill Proficiencies:</strong>&nbsp;Survival, and either Athletics or Intimidation.</p>\n<p class=\"Indent1\"><strong>Tool Proficiencies:</strong>&nbsp;Herbalism kit.</p>\n<p class=\"Indent1\"><strong>Languages:</strong>&nbsp;One of your choice.</p>\n<p class=\"Indent1\"><strong>Suggested Equipment (Cost 11&nbsp;gold):&nbsp;</strong>Traveler&rsquo;s clothes, waterskin, healer&rsquo;s kit, 7 days rations.</p>\n<p class=\"Indent1\"><strong><em>Feature: Trader.</em></strong>&nbsp;If you&rsquo;re in or near the wilderness and have a trading relationship with a tribe, settlement, or other nearby group, you can maintain a moderate lifestyle for yourself and your companions by trading the products of your hunting and gathering.</p>\n<p class=\"Indent1\"><strong><em>Adventures and Advancement</em></strong><strong>.&nbsp;</strong>During your travels, wilderness dwellers may come to you for help battling monsters and other dangers. If you succeed in several such adventures, you may earn the freely given aid of up to 8&nbsp;<span class=\"freelinking-link\">warriors</span>.</p>\n<h3><strong>OUTLANDER CONNECTIONS</strong></h3>\n<ol>\n<li>A tribal chief who owes a favor.</li>\n<li>The chief of a band of marauders who has a grudge against you.</li>\n<li>A hag to whom you owe a favor.</li>\n<li>An alchemist or wizard who frequently gives you requests for rare herbs or trophies.</li>\n<li>A unicorn you&rsquo;ve glimpsed but never been able to approach.</li>\n<li>Another outlander: your former best friend who is now a bitter rival.</li>\n<li>A wise oracle who knows most of what happens in the wilderness and will reveal it for a price.</li>\n<li>A zany prospector who knows the wild lands almost as well as you.</li>\n<li>A circus or arena owner who will pay for live animals not yet in their menagerie.</li>\n<li>A highly civilized poet or painter who has paid you to guide them to wild and inspiring locales.</li>\n</ol>\n<hr>\n<h3><strong>OUTLANDER MEMENTOS</strong></h3>\n<ol>\n<li>A trophy from the hunt of a mighty beast, such as an&nbsp;phase monster-horn helmet.</li>\n<li>A trophy from a battle against a fierce monster, such as a still-wriggling troll finger.</li>\n<li>A stone from a holy druidic shrine.</li>\n<li>Tools appropriate to your home terrain, such as pitons or snowshoes.</li>\n<li>Hand-crafted leather armor, hide armor, or clothing.</li>\n<li>The handaxe you made yourself.</li>\n<li>A gift from a dryad or faun.</li>\n<li>Trading goods worth 30 gold, such as furs or rare herbs.</li>\n<li>A tiny whistle given to you by a sprite.</li>\n<li>An incomplete map.</li>\n</ol>",
		"schemaVersion": {
			"version": 0.01,
			"lastMigration": null
		},
		"grants": {
			"rR459EOgj2QzAmRD": {
				"grantType": "ability",
				"level": 0,
				"optional": false,
				"_id": "rR459EOgj2QzAmRD",
				"default": true,
				"img": "",
				"label": "Ability Score Increase",
				"abilities": {
					"base": [
						"con"
					],
					"options": [
						"str",
						"dex",
						"con",
						"int",
						"wis",
						"cha"
					],
					"total": 1
				},
				"bonus": "1",
				"context": {
					"types": [
						"base"
					],
					"requiresProficiency": false
				}
			},
			"nlZoMsCfpUZJVxo3": {
				"grantType": "proficiency",
				"level": 0,
				"optional": false,
				"_id": "nlZoMsCfpUZJVxo3",
				"default": true,
				"img": "",
				"label": "Skill Proficiencies",
				"keys": {
					"base": [
						"sur"
					],
					"options": [
						"ath",
						"itm"
					],
					"total": 1
				},
				"proficiencyType": "skill"
			},
			"zQYeEAsszXDjug2R": {
				"grantType": "trait",
				"level": 0,
				"optional": false,
				"_id": "zQYeEAsszXDjug2R",
				"default": true,
				"img": "",
				"label": "Tool Proficiencies",
				"traits": {
					"base": [
						"herbalismKit"
					],
					"options": [],
					"total": 0,
					"traitType": "tools"
				}
			},
			"7hGt33SbKReHCgsp": {
				"grantType": "trait",
				"level": 0,
				"optional": false,
				"_id": "7hGt33SbKReHCgsp",
				"default": true,
				"img": "",
				"label": "Languages",
				"traits": {
					"base": [],
					"options": [
						"abyssal",
						"aquan",
						"auran",
						"celestial",
						"common",
						"deep",
						"draconic",
						"druidic",
						"dwarvish",
						"elvish",
						"giant",
						"gnoll",
						"gnomish",
						"goblin",
						"grimlock",
						"halfling",
						"ignan",
						"infernal",
						"minotaur",
						"mycelial",
						"orc",
						"primordial",
						"sylvan",
						"terran",
						"cant",
						"undercommon"
					],
					"total": 1,
					"traitType": "languages"
				}
			},
			"WxHYnEVk8ipfMq25": {
				"grantType": "item",
				"level": 0,
				"optional": true,
				"_id": "WxHYnEVk8ipfMq25",
				"default": true,
				"img": "",
				"label": "Suggested Equipment",
				"items": {
					"base": [],
					"options": [
						{
							"uuid": "Compendium.a5e.a5e-adventuring-gear.Item.yd87og78egvpztx3",
							"quantityOverride": 0
						},
						{
							"uuid": "Compendium.a5e.a5e-adventuring-gear.Item.wq2j5haomxdeje3m",
							"quantityOverride": 0
						},
						{
							"uuid": "Compendium.a5e.a5e-adventuring-gear.Item.067o6hjosd8nrjs8",
							"quantityOverride": 0
						},
						{
							"uuid": "Compendium.a5e.a5e-adventuring-gear.Item.pwgkdtzl4t3n9xrr",
							"quantityOverride": "7"
						}
					],
					"total": 1
				}
			},
			"rGcr9gqMvuEffe09": {
				"grantType": "feature",
				"level": 0,
				"optional": false,
				"label": "Feature",
				"features": {
					"base": [
						"Compendium.a5e.a5e-background-features.Item.h2ck63vikkdohn8a"
					]
				}
			}
		},
		"source": "adventurersGuide"
	},
	"effects": [],
	"flags": {},
	"folder": null,
	"_id": "xeq1n7f1xcps8wg8"
}