{
	"folder": null,
	"name": "Sound Sculptor's Tools",
	"type": "feature",
	"img": "icons/magic/sonic/scream-wail-shout-teal.webp",
	"system": {
		"ac": {
			"baseFormula": "",
			"formula": "",
			"maxDex": 0,
			"minStr": 0,
			"mode": 2,
			"requiresNoShield": false,
			"requiresUnarmored": false
		},
		"actions": {},
		"description": "<p>When you select this archetype at 3rd level, you gain proficiency with the Performance skill and two musical instruments of your choice. If you are already proficient in Performance, you gain an&nbsp;<span class=\"freelinking-link\">expertise die</span>&nbsp;instead. You also learn the<em>&nbsp;<span class=\"freelinking-link\">@UUID[Compendium.a5e.a5e-spells.Item.4gcxix2l4zvy9kdu]{Message}</span></em>,<em>&nbsp;<span class=\"freelinking-link\">@UUID[Compendium.a5e.a5e-spells.Item.4oruofw2q7gso9hq]{Minor Illusion}</span></em>, and&nbsp;<em><span class=\"freelinking-link\">@UUID[Compendium.a5e.a5e-spells.Item.eiek2vbzwijd0qac]{Thaumaturgy}</span></em><em>&nbsp;</em>cantrips, and they do not count against your maximum cantrips known.</p>",
		"favorite": false,
		"secretDescription": "",
		"source": {
			"name": "",
			"link": "",
			"publisher": ""
		},
		"uses": {
			"value": null,
			"max": "",
			"per": null,
			"recharge": {
				"formula": "1d6",
				"threshold": "6"
			}
		},
		"schema": {
			"version": null,
			"lastMigration": null
		},
		"concentration": false,
		"featureType": "class",
		"grants": {},
		"prerequisite": ""
	},
	"effects": [],
	"flags": {},
	"_id": "tfp7rlx6nqur12ss"
}