{
	"name": "Style: Unarmed Fighting",
	"type": "feature",
	"img": "icons/svg/item-bag.svg",
	"effects": [],
	"flags": {},
	"system": {
		"ac": {
			"baseFormula": "",
			"formula": "",
			"maxDex": 0,
			"minStr": 0,
			"mode": 2,
			"requiresNoShield": false,
			"requiresUnarmored": false
		},
		"actions": {},
		"description": "<p>Your unarmed strikes deal bludgeoning damage equal to 1d6 + your Strength modifier. If you aren’t wielding any weapons or a shield, you can strike with both of your hands to deal damage equal to 1d8 + your Strength modifier. If&nbsp;you start your turn grappling a creature, you may deal your basic melee damage to any creature you are grappling.</p>",
		"favorite": false,
		"secretDescription": "",
		"source": "",
		"uses": {
			"value": null,
			"max": "",
			"per": null,
			"recharge": {
				"formula": "1d6",
				"threshold": 6
			}
		},
		"schema": {
			"version": null,
			"lastMigration": null
		},
		"concentration": false,
		"featureType": "class",
		"grants": {},
		"prerequisite": "",
		"schemaVersion": {
			"version": 0.01,
			"lastMigration": {
				"version": {
					"schema": 0.009,
					"foundry": "12.316",
					"system": "0.16.12"
				}
			}
		}
	},
	"folder": null,
	"_id": "8go9z2qyufbmcens"
}