{
	"name": "Sweeping Stride",
	"type": "feature",
	"img": "icons/svg/item-bag.svg",
	"system": {
		"actions": {
			"KcJkydfU33MIVY4A": {
				"name": "Sweeping Stride",
				"activation": {
					"cost": "",
					"type": "",
					"reactionTrigger": ""
				},
				"duration": {
					"unit": "",
					"value": ""
				},
				"area": {
					"shape": "",
					"placeTemplate": false
				},
				"target": {
					"quantity": 1,
					"type": "creature"
				},
				"prompts": {
					"2xGvQQ5y5qXmYDSd": {
						"ability": "dex",
						"onSave": "Not prone",
						"saveDC": {
							"type": "custom",
							"bonus": "8+@prof+@int.mod"
						},
						"type": "savingThrow"
					}
				},
				"consumers": {}
			}
		},
		"description": "<p>When you move at least 10 feet and enter a space adjacent to a creature no more than one size larger than you, you can try to trip it. If the creature fails a Dexterity saving throw , it falls prone . If it succeeds, instead your movement ends in the space you entered to use this ability.</p>",
		"favorite": false,
		"secretDescription": "",
		"source": "",
		"uses": {
			"value": null,
			"max": "",
			"per": null,
			"recharge": {
				"formula": "1d6",
				"threshold": 6
			}
		},
		"schema": {
			"version": 0.003,
			"lastMigration": {
				"version": {
					"schema": null,
					"foundry": "10.291",
					"system": "0.10.7"
				}
			}
		},
		"featureType": "class",
		"prerequisite": ""
	},
	"effects": [],
	"flags": {
		"core": {
			"sourceId": "Compendium.a5e.a5e-class-features.nd9r8bgj96om9rl2"
		}
	},
	"_id": "nd9r8bgj96om9rl2"
}