{
	"folder": null,
	"name": "Medic",
	"type": "archetype",
	"img": "icons/magic/life/heart-hand-gold-green-light.webp",
	"system": {
		"description": "<p>Any number of healthcare-facing scientists might be called medics, including high-tech field doctors, medical researchers, and directors of medicine and personnel health. Most medics are oathbound to preserve life and uphold quality of life to the best of their ability. Invariably, the medic's field of deployment, cultural upbringing, and species impact how they interpret and fulfill this oath. Then there are medics who misinterpret or renege their oath, whose hatred for life or love of power drive them to commit unspeakable atrocities in the name of \"research\" and \"progress.\" As voidrunners, medics are known for their efficient use of medical supplies and their ability to promote both survival and long-term health, even on alien worlds.</p>\n<p><strong>Table: Medic<br></strong></p>\n<table border=\"1\"><colgroup><col><col></colgroup>\n<thead>\n<tr style=\"text-align: center;\">\n<td>Level</td>\n<td>Features</td>\n</tr>\n</thead>\n<tbody>\n<tr style=\"text-align: center;\">\n<td>1st</td>\n<td>@UUID[Compendium.a5e.a5e-class-features.Item.36O4SfhV4kMv1MnN]{Medical Training} @UUID[Compendium.a5e.a5e-class-features.Item.xsRpZ2TocCvKDXxX]{Tools of Science} @UUID[Compendium.a5e.a5e-class-features.Item.MOIwgRHrh5nBURKW]{Analytical Attack} @UUID[Compendium.a5e.a5e-class-features.Item.lfonYS62HJxKAawA]{Emergency Medic}</td>\n</tr>\n<tr style=\"text-align: center;\">\n<td>2nd</td>\n<td>@UUID[Compendium.a5e.a5e-class-features.Item.LjOF7wnogbDcXwVR]{Fortify Ally}</td>\n</tr>\n<tr style=\"text-align: center;\">\n<td>6th</td>\n<td>@UUID[Compendium.a5e.a5e-class-features.Item.0f5HXhLNAROGRaTE]{Designated Patients}</td>\n</tr>\n<tr style=\"text-align: center;\">\n<td>10th</td>\n<td>@UUID[Compendium.a5e.a5e-class-features.Item.RY7JgR13eEZR7xBS]{Medical Requisition}</td>\n</tr>\n<tr style=\"text-align: center;\">\n<td>14th</td>\n<td>@UUID[Compendium.a5e.a5e-class-features.Item.pVMpKynCNyzrmDW3]{Regenerative Nanites}</td>\n</tr>\n</tbody>\n</table>",
		"favorite": false,
		"macro": "",
		"migrationData": {
			"version": null,
			"type": "",
			"lastMigration": {
				"schema": null
			}
		},
		"secretDescription": "",
		"source": "voidrunnersCodex",
		"slug": "",
		"class": "scientist",
		"grants": {
			"8nUAej8SLGWlZI73": {
				"grantType": "feature",
				"level": 1,
				"levelType": "class",
				"optional": false,
				"_id": "8nUAej8SLGWlZI73",
				"label": "1st Level Archetype Features",
				"img": "",
				"features": {
					"base": [
						{
							"uuid": "Compendium.a5e.a5e-class-features.Item.36O4SfhV4kMv1MnN",
							"name": "Medical Training",
							"img": "icons/magic/life/cross-worn-green.webp",
							"limitedReselection": true,
							"selectionLimit": 1
						},
						{
							"uuid": "Compendium.a5e.a5e-class-features.Item.xsRpZ2TocCvKDXxX",
							"name": "Tools of Science",
							"img": "icons/commodities/treasure/plaque-stone-hammer.webp",
							"limitedReselection": true,
							"selectionLimit": 1
						},
						{
							"uuid": "Compendium.a5e.a5e-class-features.Item.MOIwgRHrh5nBURKW",
							"name": "Analytical Attack",
							"img": "icons/skills/targeting/crosshair-arrowhead-blue.webp",
							"limitedReselection": true,
							"selectionLimit": 1
						},
						{
							"uuid": "Compendium.a5e.a5e-class-features.Item.lfonYS62HJxKAawA",
							"limitedReselection": true,
							"selectionLimit": 1
						}
					],
					"options": [],
					"total": 0
				}
			},
			"dpk0dwalng28Da8n": {
				"grantType": "feature",
				"level": 2,
				"levelType": "class",
				"optional": false,
				"_id": "dpk0dwalng28Da8n",
				"label": "2nd Level Archetype Features",
				"img": "",
				"features": {
					"base": [
						{
							"uuid": "Compendium.a5e.a5e-class-features.Item.LjOF7wnogbDcXwVR",
							"limitedReselection": true,
							"selectionLimit": 1
						}
					],
					"options": [],
					"total": 0
				},
				"name": "undefined (Copy)"
			},
			"bvDXuDDAxxCJI5Ze": {
				"grantType": "feature",
				"level": 6,
				"levelType": "class",
				"optional": false,
				"_id": "bvDXuDDAxxCJI5Ze",
				"label": "6th Level Archetype Features",
				"img": "",
				"features": {
					"base": [
						{
							"uuid": "Compendium.a5e.a5e-class-features.Item.0f5HXhLNAROGRaTE",
							"limitedReselection": true,
							"selectionLimit": 1
						}
					],
					"options": [],
					"total": 0
				},
				"name": "undefined (Copy)"
			},
			"32oE9eKJpO61VWnG": {
				"grantType": "feature",
				"level": 10,
				"levelType": "class",
				"optional": false,
				"_id": "32oE9eKJpO61VWnG",
				"label": "10th Level Archetype Features",
				"img": "",
				"features": {
					"base": [
						{
							"uuid": "Compendium.a5e.a5e-class-features.Item.RY7JgR13eEZR7xBS",
							"limitedReselection": true,
							"selectionLimit": 1
						}
					],
					"options": [],
					"total": 0
				},
				"name": "undefined (Copy)"
			},
			"vm00kHTLMcJ80cCq": {
				"grantType": "feature",
				"level": 14,
				"levelType": "class",
				"optional": false,
				"_id": "32oE9eKJpO61VWnG",
				"label": "14th Level Archetype Features",
				"img": "",
				"features": {
					"base": [
						{
							"uuid": "Compendium.a5e.a5e-class-features.Item.pVMpKynCNyzrmDW3",
							"limitedReselection": true,
							"selectionLimit": 1
						}
					],
					"options": [],
					"total": 0
				},
				"name": "undefined (Copy)"
			}
		},
		"resources": [
			{
				"name": "Emergency Medic",
				"consumable": false,
				"displayOnCore": false,
				"reference": {
					"1": "2d6",
					"2": "2d6",
					"3": "2d6",
					"4": "2d6",
					"5": "2d6",
					"6": "4d6",
					"7": "4d6",
					"8": "4d6",
					"9": "4d6",
					"10": "4d6",
					"11": "4d6",
					"12": "6d6",
					"13": "6d6",
					"14": "6d6",
					"15": "6d6",
					"16": "6d6",
					"17": "6d6",
					"18": "8d6",
					"19": "8d6",
					"20": "8d6"
				},
				"recovery": "",
				"slug": "emergency-medic"
			}
		],
		"spellcasting": {
			"ability": {
				"base": "none",
				"options": [],
				"value": "none"
			},
			"casterType": "none"
		}
	},
	"effects": [],
	"flags": {},
	"_stats": {
		"coreVersion": "12.331",
		"systemId": "a5e",
		"systemVersion": "1.0.3",
		"createdTime": 1735915621919,
		"modifiedTime": 1735915769297,
		"lastModifiedBy": "Glw114cHAVexdKTu"
	},
	"_id": "uwgukkycpTLEchH3"
}
