{
	"folder": null,
	"name": "Reason",
	"type": "destiny",
	"img": "icons/commodities/biological/organ-brain-pink.webp",
	"system": {
		"description": "<p><strong><em>Source of Inspiration:</em> Logical Thinking.</strong> You apply your rational thought processes to every problem. You gain inspiration when you critically succeed at an Intelligence check or successfully save against the charmed, confused, frightened, or rattled conditions.</p>\n<p><strong><em>Inspiration Feature:</em> Application of Reason.</strong> You gain an expertise die whenever you make an Intelligence check.</p>\n<h3>Fulfilling Your Destiny</h3>\n<p>You fulfill your destiny of reason when you overcome the limits placed upon you by the vagaries and uncertainty of emotion and make a major sacrifice which is logical but emotionally painful.</p>\n<blockquote>\n<p>Willingly face near-certain death for the benefit of the many, choose a logical action over the life of a loved one.</p>\n</blockquote>\n<p><strong><em>Fulfillment Feature:</em> Calm Rationality.</strong> Whatever the circumstance, you act with equanimity and care. Whenever you make an ability check, you may treat rolls of less than 10 as being a roll of 10.</p>",
		"favorite": false,
		"secretDescription": "",
		"source": "voidrunnersCodex",
		"sourceOfInspiration": "Compendium.a5e.a5e-destiny-features.Item.lJHPhalDic2hubGF",
		"inspirationFeature": "Compendium.a5e.a5e-destiny-features.Item.ZZeh4WuWa1HYO6Ll",
		"fulfillmentFeature": "Compendium.a5e.a5e-destiny-features.Item.ZYeSoQDMTkenZn4B",
		"actions": {}
	},
	"effects": [],
	"flags": {},
	"_stats": {
		"coreVersion": "12.331",
		"systemId": "a5e",
		"systemVersion": "0.19.32",
		"createdTime": 1732978980254,
		"modifiedTime": 1732979114960,
		"lastModifiedBy": "Glw114cHAVexdKTu"
	},
	"_id": "JuNqyw0QfeSwSWn2"
}
