{
  "name": "Chromatic Dragon’s Boon (Dragonbound)",
  "type": "feature",
  "img": "icons/creatures/reptiles/dragon-horned-blue.webp",
  "effects": [],
  "flags": {
    "core": {
      "sourceId": "Compendium.a5e.a5e-culture-features.5y9uh4uqo9h8jo8q"
    },
    "exportSource": {
      "world": "a5e-dev",
      "system": "a5e",
      "coreVersion": "10.291",
      "systemVersion": "0.8.15"
    }
  },
  "system": {
    "ability": "",
    "actionOptions": [],
    "actions": {},
    "activation": {
      "cost": "",
      "type": "",
      "reactionTrigger": ""
    },
    "attack": {
      "bonus": "",
      "critThreshold": 20,
      "type": ""
    },
    "area": {
      "shape": "",
      "size": ""
    },
    "check": {
      "ability": "str"
    },
    "damage": [],
    "description": "<p>Chromatic dragons raise their warriors to shock and terrify their enemies. You can cast fear without the need for material components once per long rest. Your spellcasting ability for this spell is Charisma. Until you reach 5th level, the area of this casting of the spell is limited to a 15-foot cone.</p>",
    "duration": {
      "unit": "",
      "value": ""
    },
    "favorite": false,
    "healing": [],
    "proficient": true,
    "range": [],
    "save": {
      "dc": "",
      "onSave": "",
      "targetAbility": ""
    },
    "secretDescription": "",
    "source": "",
    "target": {
      "quantity": "",
      "type": ""
    },
    "uses": {
      "value": null,
      "max": "",
      "per": null
    },
    "featureType": "culture",
    "prerequisite": ""
  },
  "_stats": {
    "systemId": "a5e",
    "systemVersion": "0.8.15",
    "coreVersion": "10.291",
    "createdTime": 1678672795971,
    "modifiedTime": 1678672795971,
    "lastModifiedBy": "eunZYRLVMq93MkmD"
  }
}