{
  "name": "Magic of the Evil Eye",
  "type": "feature",
  "img": "icons/magic/perception/eye-ringed-glow-angry-large-teal.webp",
  "effects": [],
  "folder": "V5ACo6aY27qNyCTm",
  "flags": {
    "core": {},
    "exportSource": {
      "world": "a5e-dev",
      "system": "a5e",
      "coreVersion": "11.315",
      "systemVersion": "0.18.11"
    }
  },
  "system": {
    "ac": {
      "baseFormula": "",
      "formula": "",
      "grantsDisadvantage": false,
      "maxDex": 0,
      "minStr": 0,
      "mode": 2,
      "requiresNoShield": false,
      "requiresUnarmored": false
    },
    "actions": {},
    "description": "<p>You know the chill touch cantrip. Once you reach 3rd level, you can cast bane once per long rest. At 5th level, you can cast mental grip once per long rest. You don’t need material components for these spells, and your spellcasting ability for them is Intelligence, Wisdom, or Charisma (whichever is highest).</p>",
    "favorite": false,
    "secretDescription": "",
    "source": "moarComplete",
    "uses": {
      "value": 1,
      "max": "1",
      "per": "longRest",
      "recharge": {
        "formula": "1d6",
        "threshold": 6
      }
    },
    "concentration": false,
    "featureType": "culture",
    "grants": {},
    "prerequisite": "",
    "requiresBloodied": false,
    "schemaVersion": {
      "version": 0.019,
      "lastMigration": {
        "version": {
          "schema": 0.018,
          "foundry": "11.315",
          "system": "0.18.11"
        }
      }
    },
    "classes": ""
  },
  "_stats": {
    "systemId": "a5e",
    "systemVersion": "0.18.11",
    "coreVersion": "11.315",
    "createdTime": 1715599701211,
    "modifiedTime": 1715599752533,
    "lastModifiedBy": "w2w5xxtHicJQ36ch"
  }
}