{
	"name": "Victorious Hymn",
	"type": "feature",
	"img": "icons/skills/trades/music-singing-voice-blue.webp",
	"effects": [],
	"flags": {},
	"system": {
		"ac": {
			"baseFormula": "",
			"formula": "",
			"grantsDisadvantage": false,
			"maxDex": 0,
			"minStr": 0,
			"mode": 2,
			"requiresNoShield": false,
			"requiresUnarmored": false
		},
		"actions": {},
		"description": "<p>Also at 3rd level, your battle hymns take a different tone, now specially prepared for bloody fights and hard fought victories. You learn an additional battle hymn chosen from Table: Battle Hymns, counting your bard level as double for the purposes of which battle hymns you meet the prerequisites for. This battle hymn does not count against your number of battle hymns known. When you reach 8th level, you may change one of your battle hymns for a new Victorious Hymn.</p>",
		"favorite": false,
		"secretDescription": "",
		"source": "adventurersGuide",
		"uses": {
			"value": 0,
			"max": "",
			"per": "",
			"recharge": {
				"formula": "1d6",
				"threshold": 6
			}
		},
		"concentration": false,
		"featureType": "class",
		"grants": {
			"2rD3H1ouCXb6gXDR": {
				"grantType": "feature",
				"level": 1,
				"levelType": "character",
				"optional": false,
				"_id": "2rD3H1ouCXb6gXDR",
				"label": "Victorious Hymn",
				"features": {
					"total": 1,
					"options": [
						{
							"uuid": "Compendium.a5e.a5e-class-features.Item.kl7koxuwp6edgi9y",
							"name": "Harmony of Pain",
							"img": "icons/skills/trades/music-notes-sound-blue.webp",
							"limitedReselection": true,
							"selectionLimit": 1
						},
						{
							"uuid": "Compendium.a5e.a5e-class-features.Item.99b04hvh44uuv8av",
							"name": "Battle Hymn: Overbearing Rhythm",
							"img": "icons/skills/trades/music-notes-sound-blue.webp",
							"limitedReselection": true,
							"selectionLimit": 1
						},
						{
							"uuid": "Compendium.a5e.a5e-class-features.Item.am5r25ebgscf2273",
							"name": "Battle Hymn: Song of Clarity",
							"img": "icons/skills/trades/music-notes-sound-blue.webp",
							"limitedReselection": true,
							"selectionLimit": 1
						},
						{
							"uuid": "Compendium.a5e.a5e-class-features.Item.6prqen2qfzmnpbxg",
							"name": "Battle Hymn: Bastions of Justice",
							"img": "icons/skills/trades/music-notes-sound-blue.webp",
							"limitedReselection": true,
							"selectionLimit": 1
						},
						{
							"uuid": "Compendium.a5e.a5e-class-features.Item.w809qy93c5f33t2x",
							"name": "Battle Hymn: Call to Arms",
							"img": "icons/skills/trades/music-notes-sound-blue.webp",
							"limitedReselection": true,
							"selectionLimit": 1
						},
						{
							"uuid": "Compendium.a5e.a5e-class-features.Item.fjy7opusafsr55r1",
							"limitedReselection": true,
							"selectionLimit": 1
						}
					]
				}
			}
		},
		"prerequisite": "",
		"requiresBloodied": false,
		"classes": "bard",
		"class": ""
	},
	"folder": null,
	"_stats": {
		"coreVersion": "12.330",
		"systemId": "a5e",
		"systemVersion": "0.19.19",
		"createdTime": 1722310582834,
		"modifiedTime": 1722310680603,
		"lastModifiedBy": "Glw114cHAVexdKTu"
	},
	"_id": "sny09r6fr2fo0xtu"
}