{
	"folder": null,
	"name": "Officer’s Academy",
	"type": "feature",
	"img": "icons/magic/control/control-influence-rally-purple.webp",
	"system": {
		"ac": {
			"baseFormula": "",
			"formula": "",
			"grantsDisadvantage": false,
			"maxDex": 0,
			"minStr": 0,
			"mode": 2,
			"requiresNoShield": false,
			"requiresUnarmored": false
		},
		"actions": {},
		"description": "<p>You got your education by virtue of your proximity to a military force, where learning is not for its own sake but for the sake of the security of your people.&nbsp;You have a military rank and title (unless you have retired from service), potentially opening doors that would not be available to a civilian.&nbsp;You gain proficiency with Insight. You also gain an expertise die on opposed rolls against Intimidation checks and saves made to resist fear effects.</p>",
		"favorite": false,
		"secretDescription": "",
		"source": "voidrunnersCodex",
		"uses": {
			"value": 0,
			"max": "",
			"per": "",
			"recharge": {
				"formula": "",
				"threshold": 0
			}
		},
		"concentration": false,
		"featureType": "class",
		"grants": {
			"RQHWdi9p6eI1G3ah": {
				"grantType": "skill",
				"level": 1,
				"levelType": "character",
				"optional": false,
				"_id": "RQHWdi9p6eI1G3ah",
				"skills": {
					"base": [
						"ins"
					]
				},
				"label": "Officer’s Academy"
			}
		},
		"prerequisite": "",
		"requiresBloodied": false,
		"class": "",
		"classes": "scientist",
		"migrationData": {
			"version": 0.019,
			"lastMigration": {
				"system": null,
				"foundry": null,
				"schema": null
			},
			"type": ""
		}
	},
	"effects": [],
	"flags": {},
	"_stats": {
		"coreVersion": "12.331",
		"systemId": "a5e",
		"systemVersion": "0.19.32",
		"createdTime": 1733516061287,
		"modifiedTime": 1733668633557,
		"lastModifiedBy": "Glw114cHAVexdKTu"
	},
	"_id": "imFZETj1nQoR8nUn"
}
