{
	"folder": null,
	"name": "Gatesealer",
	"type": "feature",
	"img": "icons/magic/symbols/ring-circle-smoke-blue.webp",
	"system": {
		"ac": {
			"baseFormula": "",
			"formula": "",
			"grantsDisadvantage": false,
			"maxDex": 0,
			"minStr": 0,
			"mode": 2,
			"requiresNoShield": false,
			"requiresUnarmored": false
		},
		"actions": {},
		"description": "<blockquote><p>You learn specialized magic usually only entrusted to the servants of the gods.</p></blockquote><p>You add the <em>Dispel Evil and Good</em> and <em>Hallow</em> spells to your spellbook.</p><p>You also add the <em>Forbiddance</em> spell at level 11, the <em>Divine Ward</em> spell at level 13, and the&nbsp;<em>Antimagic Field</em> spell at level 15. None of these spells count against your wizard spell choices for their respective levels.</p><p>You also learn the <em>Break Spell</em> maneuver and your exertion pool increases by 2 points. If you already know it, you may choose another 2nd- or 3rd- degree maneuver from the <em>Tempered Iron</em> school or from another combat tradition that utilizes or nullifies magic.</p><p>Finally, you gain advantage on saving throws to avoid taking <em>psychic</em> damage or gaining levels of strife from any source but your own spells or features.</p>",
		"favorite": false,
		"secretDescription": "",
		"source": "thematicToolkitHazardousKnowledge",
		"uses": {
			"value": 0,
			"max": "",
			"per": "",
			"recharge": {
				"formula": "1d6",
				"threshold": 6
			}
		},
		"concentration": false,
		"featureType": "class",
		"grants": {},
		"prerequisite": "Wizard level 10, Proscriber archetype",
		"requiresBloodied": false,
		"schemaVersion": {
			"version": 0.019,
			"lastMigration": {
				"version": {
					"schema": 0.018,
					"foundry": "11.315",
					"system": "0.18.11"
				}
			}
		},
		"classes": ""
	},
	"effects": [],
	"flags": {},
	"_id": "jygh2wkj7gi5zx0x",
	"_stats": {
		"coreVersion": "12",
		"systemId": "a5e",
		"systemVersion": "0.19.14"
	}
}