{
	"folder": null,
	"name": "Child of the Elements (Earth)",
	"type": "feature",
	"img": "icons/magic/symbols/elements-air-earth-fire-water.webp",
	"system": {
		"ac": {
			"baseFormula": "",
			"formula": "",
			"grantsDisadvantage": false,
			"maxDex": 0,
			"minStr": 0,
			"mode": 2,
			"requiresNoShield": false,
			"requiresUnarmored": false
		},
		"actions": {},
		"description": "<p>You gain resistance to certain damage types: Non-magical Slashing</p>",
		"favorite": false,
		"secretDescription": "",
		"source": "moarComplete",
		"uses": {
			"value": 0,
			"max": "",
			"per": "",
			"recharge": {
				"formula": "",
				"threshold": 0
			}
		},
		"concentration": false,
		"featureType": "heritage",
		"grants": {
			"ibd5OvWNxPIgkgAL": {
				"grantType": "trait",
				"level": 0,
				"optional": false,
				"label": "Child of the Elements (Earth)",
				"traits": {
					"base": [
						"slashing"
					],
					"options": [],
					"total": 0,
					"traitType": "damageResistances"
				}
			}
		},
		"prerequisite": "",
		"requiresBloodied": false,
		"schemaVersion": {
			"version": 0.016,
			"lastMigration": {
				"version": {
					"schema": 0.015,
					"foundry": "11.315",
					"system": "0.17.33"
				}
			}
		}
	},
	"effects": [],
	"flags": {},
	"_id": "53lj7tl8ltv1eb3v"
}