{
	"folder": null,
	"name": "Winter Coat",
	"type": "feature",
	"img": "icons/commodities/leather/fur-brown-gold.webp",
	"system": {
		"ac": {
			"baseFormula": "",
			"formula": "",
			"grantsDisadvantage": false,
			"maxDex": 0,
			"minStr": 0,
			"mode": 2,
			"requiresNoShield": false,
			"requiresUnarmored": false
		},
		"actions": {},
		"description": "<p>You gain resistance to cold damage.</p>",
		"favorite": false,
		"secretDescription": "",
		"source": "",
		"uses": {
			"value": 0,
			"max": "",
			"per": "",
			"recharge": {
				"formula": "",
				"threshold": 0
			}
		},
		"concentration": false,
		"featureType": "heritage",
		"grants": {
			"xibaMWEPjyMu6X2n": {
				"grantType": "trait",
				"level": 1,
				"levelType": "character",
				"optional": false,
				"label": "Cold Resistance",
				"traits": {
					"base": [
						"cold"
					],
					"options": [],
					"total": 0,
					"traitType": "damageResistances"
				}
			}
		},
		"prerequisite": "",
		"requiresBloodied": false,
		"classes": ""
	},
	"effects": [],
	"flags": {},
	"_id": "9bpqo4ykao8vu8yo",
	"_stats": {
		"coreVersion": "12",
		"systemId": "a5e",
		"systemVersion": "0.19.17"
	}
}
