{
	"name": "Firespark",
	"type": "maneuver",
	"img": "icons/skills/ranged/arrows-flying-salvo-blue-light.webp",
	"system": {
		"actions": {
			"xNrB213R8Z1CHQdy": {
				"name": "Firespark",
				"activation": {
					"cost": 1,
					"type": "action",
					"reactionTrigger": ""
				},
				"duration": {
					"unit": "instantaneous",
					"value": ""
				},
				"area": {
					"shape": "",
					"placeTemplate": false
				},
				"target": {
					"quantity": 1,
					"type": "creatureObject"
				},
				"rolls": {
					"MbGxMmozHXBI4NsG": {
						"bonus": "",
						"critThreshold": "20",
						"type": "attack",
						"attackType": "rangedWeaponAttack",
						"ability": "default"
					}
				},
				"consumers": {
					"5JNNKvxSMbsk4k82": {
						"quantity": 1,
						"resource": "exertion",
						"type": "resource"
					}
				}
			}
		},
		"description": "<div class=\"page\" title=\"Page 38\">\n<div class=\"layoutArea\">\n<div class=\"column\">\n<p>With a snap of your fingers, your ranged weapon glows red with heat. Make a ranged attack roll against an unattended object. On a successful hit, unattended flammable materials ignite as if they had been directly exposed to great heat and flame. If used to attack a creature, this attack deals fire damage.</p>\n</div>\n</div>\n</div>",
		"favorite": false,
		"secretDescription": "",
		"source": {
			"name": "System Architecture: Motif Classes",
			"link": "https://bit.ly/437OgQZ",
			"publisher": "purpleMartinGames"
		},
		"uses": {
			"value": null,
			"max": null,
			"per": "",
			"recharge": {
				"formula": "1d6",
				"threshold": 6
			}
		},
		"schema": {
			"version": null,
			"lastMigration": null
		},
		"degree": "1",
		"exertionCost": 1,
		"isStance": false,
		"prerequisite": "",
		"tradition": "arcaneArtillery",
		"ability": "default",
		"proficient": true,
		"save": {
			"dc": "",
			"onSave": "",
			"targetAbility": ""
		},
		"equippedState": 0,
		"-=recharge": null,
		"-=equipped": null,
		"schemaVersion": {
			"version": 0.01,
			"lastMigration": {
				"version": {
					"schema": 0.009,
					"foundry": "12.316",
					"system": "0.16.12"
				}
			}
		}
	},
	"effects": [],
	"flags": {},
	"folder": null,
	"_id": "yx100b9letp3hy36"
}