{
	"name": "Breastplate/Cuirass (Bronze)",
	"type": "object",
	"img": "icons/equipment/chest/breastplate-sculpted-grey.webp",
	"effects": [],
	"flags": {},
	"system": {
		"ability": "",
		"actionOptions": [],
		"activation": {
			"cost": "",
			"type": "",
			"reactionTrigger": ""
		},
		"attack": {
			"bonus": "",
			"critThreshold": 20,
			"type": ""
		},
		"area": {
			"shape": "",
			"size": ""
		},
		"check": {
			"ability": "str"
		},
		"damage": [],
		"description": "<p><em>Weighty (+1)</em></p><p><strong>AC 14 (DEX +2 max)</strong></p>",
		"duration": {
			"unit": "",
			"value": ""
		},
		"favorite": false,
		"healing": [],
		"proficient": true,
		"range": [],
		"save": {
			"dc": "",
			"onSave": "",
			"targetAbility": ""
		},
		"source": "",
		"target": {
			"quantity": "",
			"type": ""
		},
		"uses": {
			"value": null,
			"max": "",
			"per": null
		},
		"ammunitionProperties": [],
		"armorCategory": "medium",
		"armorProperties": [],
		"attuned": false,
		"bulky": false,
		"equipped": false,
		"materialProperties": [
			"weighty"
		],
		"objectType": "armor",
		"plotItem": false,
		"price": "300 gp",
		"quantity": 1,
		"rarity": "common",
		"requiresAttunement": false,
		"weaponProperties": [],
		"weight": "35 lbs"
	},
	"_id": "qmn5eke4qknrjg01"
}