{
	"name": "Ring Blade",
	"type": "object",
	"img": "icons/weapons/thrown/shuriken-triple-purple.webp",
	"effects": [],
	"flags": {
		"core": {
			"sourceId": "Compendium.a5e.a5e-adventuring-gear.cydwjacfp6rb0jue"
		}
	},
	"system": {
		"ability": "default",
		"actions": {
			"PEWeqnYfJoWzrllb": {
				"name": "Ring Blade",
				"activation": {
					"cost": "",
					"type": "",
					"reactionTrigger": ""
				},
				"duration": {
					"unit": "",
					"value": ""
				},
				"ranges": {
					"s3YWCMRJAZiYwCJZ": {
						"range": "short"
					},
					"BdSRi075WUTeW3po": {
						"range": "90 ft"
					}
				},
				"area": {
					"shape": "",
					"size": "",
					"placeTemplate": false
				},
				"target": {
					"quantity": 1,
					"type": "creatureObject"
				},
				"rolls": {
					"NDpmhqKlnLyFdRhh": {
						"bonus": "",
						"critThreshold": "20",
						"type": "attack"
					},
					"yzAnaGwyjHjsSnxl": {
						"canCrit": true,
						"damageType": "slashing",
						"formula": "1d6 + @str.mod",
						"name": "Ring Blade",
						"type": "damage"
					}
				}
			}
		},
		"description": "<p><em>Thrown (30/90)</em></p><hr class=\"a5e-rule u-my-md\"><p>This metal hoop has sharpened edges that make it deadly whether thrown or used in hand.</p><p>It costs only 1 exertion point to use the <strong><em>Ricochet</em></strong><em> </em><strong><em>combat maneuver</em></strong> with this weapon. In addition, when you throw this weapon, you may make the attack with disadvantage, and on a hit it returns to your hand.</p>",
		"favorite": false,
		"proficient": true,
		"save": {
			"dc": "",
			"onSave": "",
			"targetAbility": ""
		},
		"secretDescription": "",
		"source": "",
		"uses": {
			"value": null,
			"max": "",
			"per": null
		},
		"ammunitionProperties": [],
		"armorCategory": "",
		"armorProperties": [],
		"attuned": false,
		"broken": false,
		"bulky": false,
		"craftingComponents": "",
		"equipped": false,
		"materialProperties": [],
		"objectType": "weapon",
		"plotItem": false,
		"price": "10 gp",
		"quantity": 1,
		"rarity": "rare",
		"requiresAttunement": false,
		"unidentified": false,
		"unidentifiedDescription": "",
		"unidentifiedName": "",
		"weaponProperties": [
			"thrown"
		],
		"weight": 6
	},
	"_id": "cydwjacfp6rb0jue"
}